autotyping/__init__.py
autotyping/__main__.py
autotyping/autotyping.py
autotyping/guess_type.py
autotyping-24.9.0.dist-info/METADATA
autotyping-24.9.0.dist-info/WHEEL
autotyping-24.9.0.dist-info/entry_points.txt
autotyping-24.9.0.dist-info/top_level.txt
autotyping-24.9.0.dist-info/RECORD
