Metadata-Version: 2.1
Name: autotyping
Version: 24.9.0
Summary: A tool for autoadding simple type annotations.
Author-email: Jelle Zijlstra <jelle.zijlstra@gmail.com>
Project-URL: Bug Tracker, https://github.com/JelleZijlstra/autotyping/issues
Project-URL: Homepage, https://github.com/JelleZijlstra/autotyping
Keywords: annotations,typing
Classifier: Development Status :: 3 - Alpha
Classifier: Environment :: Console
Classifier: Intended Audience :: Developers
Classifier: License :: OSI Approved :: MIT License
Classifier: Operating System :: OS Independent
Classifier: Programming Language :: Python
Classifier: Programming Language :: Python :: 3.8
Classifier: Programming Language :: Python :: 3.9
Classifier: Programming Language :: Python :: 3.10
Classifier: Programming Language :: Python :: 3.11
Classifier: Programming Language :: Python :: 3.12
Classifier: Programming Language :: Python :: 3.13
Classifier: Topic :: Software Development
Requires-Python: >=3.8
Requires-Dist: libcst
Requires-Dist: typing-extensions
